minivectordb/__init__.py
minivectordb/embedding_model.py
minivectordb/sharded_vector_database.py
minivectordb/sharded_vector_database_usearch.py
minivectordb/vector_database.py
minivectordb/resources/embedding_model_quantized.onnx
tests/__init__.py
tests/test_embedding_model.py
tests/test_mongolike_operators.py
tests/test_multithreaded_operations.py
tests/test_sharded_mongolike_operators.py
tests/test_sharded_multithreaded_operations.py
tests/test_sharded_vector_database.py
tests/test_sharded_vector_database_usearch.py
tests/test_vector_database.py
minivectordb-2.3.1.dist-info/LICENSE
minivectordb-2.3.1.dist-info/METADATA
minivectordb-2.3.1.dist-info/WHEEL
minivectordb-2.3.1.dist-info/top_level.txt
minivectordb-2.3.1.dist-info/RECORD
