Metadata-Version: 2.1
Name: minivectordb
Version: 2.3.1
Summary: A python project aimed at extracting embeddings from textual data and performing semantic search.
Author: Carlo Moro
Author-email: Carlo Moro <cnmoro@gmail.com>
Project-URL: Homepage, https://github.com/cnmoro/Mini-Vector-DB
Project-URL: Bug Tracker, https://github.com/cnmoro/Mini-Vector-DB/issues
Classifier: Programming Language :: Python :: 3
Classifier: License :: OSI Approved :: MIT License
Classifier: Operating System :: OS Independent
Requires-Python: >=3.7
License-File: LICENSE
Requires-Dist: numpy <2
Requires-Dist: transformers
Requires-Dist: faiss-cpu
Requires-Dist: torch
Requires-Dist: pytest
Requires-Dist: pytest-cov
Requires-Dist: scikit-learn
Requires-Dist: thefuzz[speedup]
Requires-Dist: FlagEmbedding
Requires-Dist: onnx
Requires-Dist: onnxruntime
Requires-Dist: onnxruntime-extensions
Requires-Dist: peft
Requires-Dist: usearch
